Metadata-Version: 2.1
Name: Extract-Media-PowerPoint
Version: 0.6
Summary: Extract video PowerPoint
Home-page: https://github.com/madyel/extract_media_ppt
Author: MaDyEl
Author-email: madyel@tutanota.com
License: MIT
Platform: UNKNOWN
